wtx_weather_mcp/__init__.py
wtx_weather_mcp-0.1.3.dist-info/WHEEL
wtx_weather_mcp-0.1.3.dist-info/entry_points.txt
wtx_weather_mcp-0.1.3.dist-info/METADATA
wtx_weather_mcp-0.1.3.dist-info/RECORD
