Metadata-Version: 2.3
Name: wtx-weather-mcp
Version: 0.1.3
Summary: 基于星图维天信天气 API 查询当前天气实况、未来天气预报等气象信息
Author: lishuai
Author-email: lishuai <lis@geovis.com.cn>
Requires-Dist: mcp[cli]>=1.25.0
Requires-Dist: requests>=2.32.5
Requires-Python: >=3.10
